udata_data_fair/__init__.py
udata_data_fair/preview.py
udata_data_fair-0.2.1.dist-info/DESCRIPTION.rst
udata_data_fair-0.2.1.dist-info/METADATA
udata_data_fair-0.2.1.dist-info/RECORD
udata_data_fair-0.2.1.dist-info/WHEEL
udata_data_fair-0.2.1.dist-info/entry_points.txt
udata_data_fair-0.2.1.dist-info/metadata.json
udata_data_fair-0.2.1.dist-info/top_level.txt
