Metadata-Version: 2.0
Name: udata-data-fair
Version: 0.2.1
Summary: Use DataFair embeds to preview data
Home-page: https://github.com/koumoul-dev/udata-data-fair
Author: Koumoul
Author-email: contact@koumoul.com
License: AGPL
Keywords: udata,harvester,data-fair
Platform: UNKNOWN
Classifier: Development Status :: 3 - Alpha
Classifier: Programming Language :: Python
Classifier: Environment :: Web Environment
Classifier: Operating System :: OS Independent
Classifier: Intended Audience :: Developers
Classifier: Topic :: System :: Software Distribution
Classifier: Programming Language :: Python
Classifier: Programming Language :: Python :: 2
Classifier: Programming Language :: Python :: 2.7
Classifier: Topic :: Software Development :: Libraries :: Python Modules
Provides-Extra: test
Requires-Dist: udata (>=1.4.0.dev)
Provides-Extra: test
Requires-Dist: httpretty (==0.8.14); extra == 'test'
Requires-Dist: mock (==2.0.0); extra == 'test'
Requires-Dist: pytest (==3.5.0); extra == 'test'
Requires-Dist: pytest-flask (==0.10.0); extra == 'test'
Requires-Dist: pytest-sugar (==0.9.1); extra == 'test'
